ls_infra/__init__.py
ls_infra/api.py
ls_infra/cli.py
ls_infra/main.py
ls_infra/core/__init__.py
ls_infra/core/collector.py
ls_infra/core/resources/__init__.py
ls_infra/core/resources/instance.py
ls_infra-0.1.2.dist-info/LICENSE
ls_infra-0.1.2.dist-info/METADATA
ls_infra-0.1.2.dist-info/WHEEL
ls_infra-0.1.2.dist-info/entry_points.txt
ls_infra-0.1.2.dist-info/top_level.txt
ls_infra-0.1.2.dist-info/RECORD
