Metadata-Version: 2.1
Name: ls-infra
Version: 0.1.2
Summary: Infrastructure management tool
License-File: LICENSE
Requires-Dist: fastapi>=0.109.0
Requires-Dist: uvicorn>=0.27.0
Requires-Dist: click>=8.1.7
Requires-Dist: boto3==1.35.76
Requires-Dist: botocore==1.35.76
